certbot_dns_norisnetwork/__init__.py
certbot_dns_norisnetwork/dns_noris.py
certbot_dns_norisnetwork-0.4.0.dist-info/LICENSE
certbot_dns_norisnetwork-0.4.0.dist-info/METADATA
certbot_dns_norisnetwork-0.4.0.dist-info/WHEEL
certbot_dns_norisnetwork-0.4.0.dist-info/entry_points.txt
certbot_dns_norisnetwork-0.4.0.dist-info/top_level.txt
certbot_dns_norisnetwork-0.4.0.dist-info/RECORD
