Metadata-Version: 2.1
Name: certbot-dns-norisnetwork
Version: 0.4.0
Summary: noris network DNS Authenticator Plugin for Certbot
Home-page: https://github.com/noris-network/certbot-dns-norisnetwork
Author: Anastasia Skoufa
Author-email: anastasia.skoufa@noris.gr
License: Apache License 2.0
Classifier: Environment :: Plugins
Classifier: Intended Audience :: System Administrators
Classifier: License :: OSI Approved :: Apache Software License
Classifier: Operating System :: OS Independent
Classifier: Programming Language :: Python :: 3
Classifier: Programming Language :: Python :: 3.9
Classifier: Programming Language :: Python :: 3.10
Classifier: Programming Language :: Python :: 3.11
Classifier: Programming Language :: Python :: 3.12
Classifier: Topic :: Internet :: Name Service (DNS)
Classifier: Topic :: Security
Classifier: Topic :: System :: Systems Administration
Classifier: Topic :: Utilities
Requires-Python: >=3.8
License-File: LICENSE
Requires-Dist: certbot==4.0.0
Requires-Dist: requests==2.32.3
Provides-Extra: dev
Requires-Dist: black; extra == "dev"
Requires-Dist: bump2version; extra == "dev"
Requires-Dist: mypy; extra == "dev"
Requires-Dist: pylint; extra == "dev"
Requires-Dist: pytest; extra == "dev"
Requires-Dist: pytest-cov; extra == "dev"
Requires-Dist: types-requests; extra == "dev"
